InsightIDR4Py.py
InsightIDR4Py-0.3.1.dist-info/LICENSE
InsightIDR4Py-0.3.1.dist-info/METADATA
InsightIDR4Py-0.3.1.dist-info/WHEEL
InsightIDR4Py-0.3.1.dist-info/top_level.txt
InsightIDR4Py-0.3.1.dist-info/RECORD
