Metadata-Version: 2.1
Name: InsightIDR4Py
Version: 0.3.1
Summary: A Python client allowing simplified interaction with Rapid7's InsightIDR REST API.
Home-page: https://github.com/mbabinski/InsightIDR4Py
Author: Micah Babinski
Author-email: m.babinski.88@gmail.com
License: MIT
Keywords: Rapid7,InsightIDR,SIEM,Logsearch,Investigations,Threats,Alerts
License-File: LICENSE
Requires-Dist: requests
